find_system_fonts_filename/__init__.py
find_system_fonts_filename/exceptions.py
find_system_fonts_filename/fonts_filename.py
find_system_fonts_filename/system_fonts.py
find_system_fonts_filename/android/__init__.py
find_system_fonts_filename/android/android.py
find_system_fonts_filename/android/android_fonts.py
find_system_fonts_filename/mac/__init__.py
find_system_fonts_filename/mac/core_foundation.py
find_system_fonts_filename/mac/core_text.py
find_system_fonts_filename/mac/mac_fonts.py
find_system_fonts_filename/mac/types.py
find_system_fonts_filename/mac/version_helpers.py
find_system_fonts_filename/unix/__init__.py
find_system_fonts_filename/unix/fontconfig.py
find_system_fonts_filename/unix/unix_fonts.py
find_system_fonts_filename/windows/__init__.py
find_system_fonts_filename/windows/advapi32.py
find_system_fonts_filename/windows/dwrite.py
find_system_fonts_filename/windows/gdi32.py
find_system_fonts_filename/windows/kernel32.py
find_system_fonts_filename/windows/msvcrt.py
find_system_fonts_filename/windows/user32.py
find_system_fonts_filename/windows/version_helpers.py
find_system_fonts_filename/windows/windows_fonts.py
findsystemfontsfilename-0.3.3.dist-info/licenses/LICENSE
findsystemfontsfilename-0.3.3.dist-info/METADATA
findsystemfontsfilename-0.3.3.dist-info/WHEEL
findsystemfontsfilename-0.3.3.dist-info/top_level.txt
findsystemfontsfilename-0.3.3.dist-info/RECORD
