Metadata-Version: 2.4
Name: FindSystemFontsFilename
Version: 0.3.3
Summary: Find the system fonts filename.
Author-email: moi15moi <moi15moismokerlolilol@gmail.com>
License-Expression: MIT
Project-URL: Source, https://github.com/moi15moi/FindSystemFontsFilename/
Project-URL: Tracker, https://github.com/moi15moi/FindSystemFontsFilename/issues/
Classifier: Development Status :: 4 - Beta
Classifier: Intended Audience :: Developers
Classifier: Programming Language :: Python
Classifier: Programming Language :: Python :: 3
Classifier: Programming Language :: Python :: 3.9
Classifier: Programming Language :: Python :: 3.10
Classifier: Programming Language :: Python :: 3.11
Classifier: Programming Language :: Python :: 3.12
Classifier: Programming Language :: Python :: 3.13
Classifier: Programming Language :: Python :: 3.14
Classifier: Operating System :: Android
Classifier: Operating System :: MacOS
Classifier: Operating System :: Microsoft :: Windows
Classifier: Operating System :: Unix
Requires-Python: >=3.9
License-File: LICENSE
Requires-Dist: comtypes>=1.4.13; platform_system == "Windows"
Provides-Extra: dev
Requires-Dist: coverage>=7.0.0; extra == "dev"
Requires-Dist: pytest>=8.0.0; extra == "dev"
Dynamic: license-file
